{
  "1": {
    "title": "Day 1 辦公室常用單字",
    "vocabulary": [
      {"word": "agenda (n.)", "zh": "議程；討論主題", "eg": "The chairperson added three new items to the meeting agenda.", "trans": "主席在會議議程中增加了三個新項目。", "hint": "會議討論項目的清單。"},
      {"word": "schedule (n.)", "zh": "日程表；進度表", "eg": "We are working hard to complete the project ahead of schedule.", "trans": "我們正努力工作，以求在預定進度之前完成這項專案。", "hint": "事情安排的時間順序或進度。"},
      {"word": "postpone (v.)", "zh": "延期、延後", "eg": "The board decided to postpone the discussion until next Tuesday.", "trans": "董事會決定將這項討論延期到下週二。", "hint": "把事情往後挪到另一個時間。"},
      {"word": "colleague (n.)", "zh": "同事", "eg": "Ms. Lin received a beautiful gift from a colleague on her last day.", "trans": "林小姐在上班的最後一天收到了一位同事送的漂亮禮物。", "hint": "在同一家公司或單位工作的人。"},
      {"word": "document (n.)", "zh": "文件", "eg": "Please review the attached document before signing the agreement.", "trans": "在簽署協議之前，請先審閱隨附的文件。", "hint": "正式的書面資料或電子檔案。"},
      {"word": "confirm (v.)", "zh": "確認、證實", "eg": "Clients must reply to this email to confirm their hotel reservations.", "trans": "客戶必須回覆這封電子郵件以確認他們的飯店預訂。", "hint": "確保某件事實或安排無誤。"},
      {"word": "notice (n.)", "zh": "通知、公告", "eg": "The office will remain closed until further notice due to renovations.", "trans": "由於裝修，辦公室將保持關閉，直到另行通知。", "hint": "正式傳達訊息的公告。"},
      {"word": "attend (v.)", "zh": "參加、出席", "eg": "All department managers are required to attend the annual conference.", "trans": "所有部門經理都必須出席年度會議。", "hint": "到場參加活動或會議。"},
      {"word": "remind (v.)", "zh": "提醒", "eg": "The assistant will remind the director about the upcoming press event.", "trans": "助理會提醒主任關於即將舉行的記者會活動。", "hint": "讓某人想起該做的事。"},
      {"word": "contact (v.)", "zh": "聯絡、接觸", "eg": "If you have any questions, please feel free to contact our support team.", "trans": "如果您有任何問題，請隨時與我們的支援團隊聯絡。", "hint": "與某人取得聯繫。"}
    ],
    "quiz": [
      {"q": "The chairperson added three new items to the meeting _______.", "options": ["agenda", "document", "colleague", "notice"], "ans": "agenda", "trans": "主席在會議議程中增加了三個新項目。"},
      {"q": "We are working hard to complete the project ahead of _______.", "options": ["contract", "strategy", "schedule", "benefit"], "ans": "schedule", "trans": "我們正努力工作，以求在預定進度之前完成這項專案。"},
      {"q": "The board decided to _______ the discussion until next Tuesday.", "options": ["attend", "postpone", "confirm", "remind"], "ans": "postpone", "trans": "董事會決定將這項討論延期到下週二。"},
      {"q": "Ms. Lin received a beautiful gift from a _______ on her last day.", "options": ["strategy", "candidate", "client", "colleague"], "ans": "colleague", "trans": "林小姐在上班的最後一天收到了一位同事送的漂亮禮物。"},
      {"q": "Please review the attached _______ before signing the agreement.", "options": ["agenda", "notice", "document", "procedure"], "ans": "document", "trans": "在簽署協議之前，請先審閱隨附的文件。"},
      {"q": "Clients must reply to this email to _______ their hotel reservations.", "options": ["confirm", "postpone", "attend", "contact"], "ans": "confirm", "trans": "客戶必須回覆這封電子郵件以確認他們的飯店預訂。"},
      {"q": "The office will remain closed until further _______ due to renovations.", "options": ["schedule", "notice", "document", "agenda"], "ans": "notice", "trans": "由於裝修，辦公室將保持關閉，直到另行通知。"},
      {"q": "All department managers are required to _______ the annual conference.", "options": ["remind", "contact", "attend", "postpone"], "ans": "attend", "trans": "所有部門經理都必須出席年度會議。"},
      {"q": "The assistant will _______ the director about the upcoming press event.", "options": ["remind", "confirm", "notice", "attend"], "ans": "remind", "trans": "助理會提醒主任關於即將舉行的記者會活動。"},
      {"q": "If you have any questions, please feel free to _______ our support team.", "options": ["postpone", "contact", "confirm", "remind"], "ans": "contact", "trans": "如果您有任何問題，請隨時與我們的支援團隊聯絡。"}
    ]
  },
  "2": {
    "title": "Day 2 會議與協商單字",
    "vocabulary": [
      {"word": "negotiate (v.)", "zh": "談判；協商", "eg": "The company is trying to negotiate a new contract with the supplier.", "trans": "公司正試圖與供應商協商一份新合約。", "hint": "討論以達成協議。"},
      {"word": "propose (v.)", "zh": "提議；建議", "eg": "I would like to propose a short break before we continue the discussion.", "trans": "我想在我們繼續討論前提議休息片刻。", "hint": "提出一個計畫或想法供考慮。"},
      {"word": "presentation (n.)", "zh": "簡報；演講", "eg": "She gave an impressive presentation on the latest market trends.", "trans": "她針對最新的市場趨勢做了一場令人印象深刻的簡報。", "hint": "向聽眾展示資訊的過程。"},
      {"word": "delegate (v.)", "zh": "委派（權限、職務）；授權", "eg": "Effective managers know how to delegate tasks to their team members.", "trans": "優秀的經理知道如何將任務委派給團隊成員。", "hint": "將職責交給他人處理。"},
      {"word": "deadline (n.)", "zh": "截止日期；期限", "eg": "We must work overtime to meet the deadline for the proposal.", "trans": "我們必須加班以趕上提案的截止日期。", "hint": "必須完成某事的最晚時間點。"},
      {"word": "minutes (n. pl.)", "zh": "會議記錄", "eg": "Could you please take the minutes during today's staff meeting?", "trans": "可以請你在今天的員工會議中做會議記錄嗎？", "hint": "會議中討論與決定事項的正式紀錄。"},
      {"word": "resolution (n.)", "zh": "（會議的）決議；正式決定", "eg": "The committee passed a resolution to increase the marketing budget.", "trans": "委員會通過了增加行銷預算的決議。", "hint": "會議中經過投票或同意後的最終決定。"},
      {"word": "signature (n.)", "zh": "簽名", "eg": "We need the director's signature on this document before we can proceed.", "trans": "我們需要董事在文件上簽名後才能繼續進行。", "hint": "代表身分或同意的手寫姓名。"},
      {"word": "approve (v.)", "zh": "核准；贊成", "eg": "The board will meet tomorrow to approve the new project plan.", "trans": "董事會將於明天開會以核准新的計畫案。", "hint": "正式同意或接受某事物。"},
      {"word": "revise (v.)", "zh": "修訂；修改", "eg": "Based on the feedback, we need to revise the financial report.", "trans": "根據回饋意見，我們需要修訂財務報告。", "hint": "為了改善或更正而改變某物。"}
    ],
    "quiz": [
      {"q": "The board of directors passed a _______ to expand the company's operations into Europe.", "options": ["resolution", "minutes", "signature", "deadline"], "ans": "resolution", "trans": "董事會通過了將公司業務拓展至歐洲的決議。"},
      {"q": "It is important for managers to _______ tasks to their staff to ensure productivity.", "options": ["negotiate", "delegate", "propose", "revise"], "ans": "delegate", "trans": "經理將任務委派給員工以確保生產力是很重要的。"},
      {"q": "The purchasing manager is scheduled to _______ the terms of the new agreement tomorrow morning.", "options": ["approve", "delegate", "negotiate", "revise"], "ans": "negotiate", "trans": "採購經理預計將於明天上午協商新協議的條款。"},
      {"q": "The marketing director gave a very persuasive _______ about the annual budget.", "options": ["presentation", "resolution", "minutes", "signature"], "ans": "presentation", "trans": "行銷總監針對年度預算做了一場非常有說服力的簡報。"},
      {"q": "All employees must submit their reports by the Friday _______ to avoid penalties.", "options": ["deadline", "minutes", "presentation", "resolution"], "ans": "deadline", "trans": "所有員工必須在週五的截止日期前提交報告，以免受罰。"},
      {"q": "Please ensure that the _______ of the meeting are distributed to all attendees by tomorrow.", "options": ["signature", "minutes", "deadline", "presentation"], "ans": "minutes", "trans": "請確保在明天前將會議記錄發送給所有與會者。"},
      {"q": "Based on the client's feedback, we need to _______ the initial architectural designs.", "options": ["approve", "revise", "propose", "delegate"], "ans": "revise", "trans": "根據客戶的回饋意見，我們需要修改初始的建築設計。"},
      {"q": "The contract is not legally binding until it contains the CEO's _______.", "options": ["signature", "resolution", "presentation", "minutes"], "ans": "signature", "trans": "合約在蓋有執行長的簽名之前是不具法律效力的。"},
      {"q": "The finance department needs to _______ the travel expenses before they can be reimbursed.", "options": ["negotiate", "approve", "propose", "delegate"], "ans": "approve", "trans": "財務部需要核准差旅費用後才能予以報銷。"},
      {"q": "I would like to _______ a new marketing strategy to reach younger customers.", "options": ["revise", "propose", "negotiate", "delegate"], "ans": "propose", "trans": "我想提議一個新的行銷策略，以接觸更年輕的客群。"}
    ]
  },
  "3": {
    "title": "Day 3 行銷與銷售",
    "vocabulary": [
      {"word": "launch (v./n.)", "zh": "發表、推出（新產品）；開辦（新事業）", "eg": "The technology startup plans to launch its new application next month.", "trans": "這家科技新創公司計劃在下個月推出其新的應用程式。", "hint": "推出新產品或服務到市場上。"},
      {"word": "campaign (n.)", "zh": "（有組織的商業或政治）活動、宣傳活動", "eg": "The marketing department is launching a new advertising campaign to attract younger customers.", "trans": "行銷部門正在發起一項新的廣告宣傳活動，以吸引年輕一代的顧客。", "hint": "有計畫的營銷推廣活動。"},
      {"word": "target (v./n.)", "zh": "以……為目標；目標、靶子", "eg": "Our current sales strategies target professionals aged 25 to 40.", "trans": "我們目前的銷售策略以 25 至 40 歲的專業人士為目標客群。", "hint": "針對特定的客群或市場。"},
      {"word": "promote (v.)", "zh": "促銷、宣傳；晉升", "eg": "The company launched a social media event to promote its organic products.", "trans": "公司舉辦了社群媒體活動來促銷其有機產品。", "hint": "透過活動或廣告宣傳某物。"},
      {"word": "feedback (n.)", "zh": "回饋意見、反應", "eg": "We welcome customer feedback as it helps us improve our services.", "trans": "我們歡迎客戶的回饋意見，因為這能幫助我們改進服務。", "hint": "客戶或使用者對產品或服務的看法。"},
      {"word": "distribution (n.)", "zh": "分銷、分配、分發", "eg": "The logistics manager is in charge of product distribution across North America.", "trans": "物流經理負責整個北美地區的產品分銷與配送。", "hint": "將產品運送到各個銷售點。"},
      {"word": "competitive (adj.)", "zh": "競爭激烈的、有競爭力的", "eg": "To stay competitive, we need to constantly innovate our product line.", "trans": "為了保持競爭力，我們需要不斷創新我們的產品線。", "hint": "能夠在市場競爭中保持優勢。"},
      {"word": "strategy (n.)", "zh": "策略、戰略", "eg": "The board of directors will discuss the long-term growth strategy tomorrow.", "trans": "董事會明天將討論長期的成長策略。", "hint": "達成目標的長期計畫。"},
      {"word": "consumer (n.)", "zh": "消費者", "eg": "Consumer spending has increased significantly during the holiday season.", "trans": "在節日期間，消費者支出有顯著的增長。", "hint": "購買或使用商品和服務的人。"},
      {"word": "analyze (v.)", "zh": "分析", "eg": "Analysts will analyze the market data to predict future trends.", "trans": "分析師將分析市場數據以預測未來的市場趨勢。", "hint": "詳細檢視和研究某事物。"}
    ],
    "quiz": [
      {"q": "The technology startup plans to _______ its new application next month.", "options": ["launch", "campaign", "strategy", "promote"], "ans": "launch", "trans": "這家科技新創公司計劃在下個月推出其新的應用程式。"},
      {"q": "The marketing department is launching a new advertising _______ to attract younger customers.", "options": ["campaign", "strategy", "feedback", "distribution"], "ans": "campaign", "trans": "行銷部門正在發起一項新的廣告宣傳活動，以吸引年輕一代的顧客。"},
      {"q": "Our current sales strategies _______ professionals aged 25 to 40.", "options": ["target", "analyze", "promote", "launch"], "ans": "target", "trans": "我們目前的銷售策略以 25 至 40 歲的專業人士為目標客群。"},
      {"q": "The company launched a social media event to _______ its organic products.", "options": ["promote", "launch", "distribute", "analyze"], "ans": "promote", "trans": "公司舉辦了社群媒體活動來促銷其有機產品。"},
      {"q": "We welcome customer _______ as it helps us improve our services.", "options": ["feedback", "input", "response", "strategy"], "ans": "feedback", "trans": "我們歡迎客戶的回饋意見，因為這能幫助我們改進服務。"},
      {"q": "The logistics manager is in charge of product _______ across North America.", "options": ["distribution", "delivery", "shipment", "strategy"], "ans": "distribution", "trans": "物流經理負責整個北美地區的產品分銷與配送。"},
      {"q": "To stay _______, we need to constantly innovate our product line.", "options": ["competitive", "active", "engaged", "strategic"], "ans": "competitive", "trans": "為了保持競爭力，我們需要不斷創新我們的產品線。"},
      {"q": "The board of directors will discuss the long-term growth _______ tomorrow.", "options": ["strategy", "plan", "direction", "approach"], "ans": "strategy", "trans": "董事會明天將討論長期的成長策略。"},
      {"q": "_______ spending has increased significantly during the holiday season.", "options": ["Consumer", "Customer", "Buyer", "Purchaser"], "ans": "Consumer", "trans": "在節日期間，消費者支出有顯著的增長。"},
      {"q": "Analysts will _______ the market data to predict future trends.", "options": ["analyze", "examine", "study", "research"], "ans": "analyze", "trans": "分析師將分析市場數據以預測未來的市場趨勢。"}
    ]
  },
  "4": {
    "title": "Day 4 財務與預算",
    "vocabulary": [
      {"word": "budget (n./v.)", "zh": "預算；編列預算", "eg": "The department was forced to cut its marketing budget for the next fiscal year.", "trans": "該部門被迫削減下一個財政年度的行銷預算。", "hint": "計畫中的財務支出安排。"},
      {"word": "expense (n.)", "zh": "費用、支出、開支", "eg": "Travel expenses must be approved by the manager before they can be reimbursed.", "trans": "差旅費用必須先經經理核准後才能申請報銷。", "hint": "為了某事而花費的金錢。"},
      {"word": "revenue (n.)", "zh": "收入、收益（常指公司或國家的總收入）", "eg": "The company reported a 15% increase in annual revenue.", "trans": "該公司報告年度總營收增長了 15%。", "hint": "公司或組織通過銷售所得到的收入。"},
      {"word": "profit (n./v.)", "zh": "利潤、收益；獲利", "eg": "Our net profits have doubled since we launched the online store.", "trans": "自從我們開設線上商店以來，我們的淨利潤已經增加了一倍。", "hint": "收入扣除所有成本和費用後的剩餘部分。"},
      {"word": "financial (adj.)", "zh": "財務的、金融的", "eg": "You should seek professional financial advice before investing a large sum of money.", "trans": "在投資大筆資金之前，你應該尋求專業的財務建議。", "hint": "與金錢和財務事務相關的。"},
      {"word": "invoice (n.)", "zh": "發票、費用清單、請款單", "eg": "Please send the invoice to our accounting department for processing.", "trans": "請將發票發送至我們的會計部門以進行後續處理。", "hint": "詳細列出商品或服務費用的文件。"},
      {"word": "invest (v.)", "zh": "投資", "eg": "The firm decided to invest millions of dollars in renewable energy research.", "trans": "該公司決定投資數百萬美元於再生能源的研究。", "hint": "把金錢投入某個事業或計畫以期獲得回報。"},
      {"word": "fund (n./v.)", "zh": "資金、基金；資助、提供資金", "eg": "The organization set up a special fund to support local startups.", "trans": "該機構設立了專門的基金來支持本地的新創企業。", "hint": "用於特定目的的資金或金錢。"},
      {"word": "transaction (n.)", "zh": "交易、買賣", "eg": "Secure encryption technology protects all online transactions from unauthorized access.", "trans": "安全的加密技術可保護所有線上交易免受未經授權的存取。", "hint": "兩方之間進行的買賣或交換活動。"},
      {"word": "deficit (n.)", "zh": "赤字、虧損", "eg": "The government is trying to reduce the budget deficit by cutting unnecessary spending.", "trans": "政府正試圖透過削減不必要的開支來減少預算赤字。", "hint": "支出大於收入所導致的短差。"}
    ],
    "quiz": [
      {"q": "The department was forced to cut its marketing _______ for the next fiscal year.", "options": ["budget", "expenses", "costs", "funds"], "ans": "budget", "trans": "該部門被迫削減下一個財政年度的行銷預算。"},
      {"q": "Travel _______ must be approved by the manager before they can be reimbursed.", "options": ["expense", "fees", "charges", "costs"], "ans": "expense", "trans": "差旅費用必須先經經理核准後才能申請報銷。"},
      {"q": "The company reported a 15% increase in annual _______.", "options": ["revenue", "profit", "income", "earnings"], "ans": "revenue", "trans": "該公司報告年度總營收增長了 15%。"},
      {"q": "Our net _______ have doubled since we launched the online store.", "options": ["profit", "revenues", "earnings", "gains"], "ans": "profit", "trans": "自從我們開設線上商店以來，我們的淨利潤已經增加了一倍。"},
      {"q": "You should seek professional _______ advice before investing a large sum of money.", "options": ["financial", "money", "investment", "monetary"], "ans": "financial", "trans": "在投資大筆資金之前，你應該尋求專業的財務建議。"},
      {"q": "Please send the _______ to our accounting department for processing.", "options": ["invoice", "receipt", "bill", "statement"], "ans": "invoice", "trans": "請將發票發送至我們的會計部門以進行後續處理。"},
      {"q": "The firm decided to _______ millions of dollars in renewable energy research.", "options": ["invest", "spend", "allocate", "commit"], "ans": "invest", "trans": "該公司決定投資數百萬美元於再生能源的研究。"},
      {"q": "The organization set up a special _______ to support local startups.", "options": ["fund", "account", "reserve", "pool"], "ans": "fund", "trans": "該機構設立了專門的基金來支持本地的新創企業。"},
      {"q": "Secure encryption technology protects all online _______ from unauthorized access.", "options": ["transaction", "transfer", "payment", "exchange"], "ans": "transaction", "trans": "安全的加密技術可保護所有線上交易免受未經授權的存取。"},
      {"q": "The government is trying to reduce the budget _______ by cutting unnecessary spending.", "options": ["deficit", "gap", "loss", "shortage"], "ans": "deficit", "trans": "政府正試圖透過削減不必要的開支來減少預算赤字。"}
    ]
  }
}
